oneday/__init__.py
oneday/component.py
oneday/exceptions.py
oneday/service.py
oneday-0.2.0.dist-info/METADATA
oneday-0.2.0.dist-info/WHEEL
oneday-0.2.0.dist-info/top_level.txt
oneday-0.2.0.dist-info/RECORD
